browser_db/__init__.py
browser_db-1.1.6.dist-info/METADATA
browser_db-1.1.6.dist-info/WHEEL
browser_db-1.1.6.dist-info/RECORD
