Metadata-Version: 2.1
Name: browser_db
Version: 1.1.6
Summary: A package used to retrieve a database of up-to-date browser JA3 fingerprints.
Author: browser-db
Requires-Python: >=3.10,<4.0
Classifier: Programming Language :: Python :: 3
Classifier: Programming Language :: Python :: 3.10
Classifier: Programming Language :: Python :: 3.11
Classifier: Programming Language :: Python :: 3.12
Requires-Dist: requests (>=2.31.0,<3.0.0)
Requires-Dist: useragent-api (>=3.1.1,<4.0.0)
